snowfall/__init__.py
snowfall/main.py
snowfall/utils.py
snowfall/generator_syncers/__init__.py
snowfall/generator_syncers/abstracts.py
snowfall/generator_syncers/database_syncer.py
snowfall/generator_syncers/simple_syncer.py
snowfall-1.0.7.dist-info/LICENSE
snowfall-1.0.7.dist-info/METADATA
snowfall-1.0.7.dist-info/WHEEL
snowfall-1.0.7.dist-info/entry_points.txt
snowfall-1.0.7.dist-info/top_level.txt
snowfall-1.0.7.dist-info/RECORD
