Metadata-Version: 2.1
Name: snowfall
Version: 1.0.7
Summary: Bigint-based distributed GUID generator
Home-page: https://github.com/lowjiajin/snowfall
Author: Low Jia Jin
Author-email: pixelrife@hotmail.com
License: MIT
Platform: UNKNOWN
Classifier: License :: OSI Approved :: MIT License
Classifier: Programming Language :: Python :: 3.7
Requires-Dist: APScheduler (==3.6.3)
Requires-Dist: SQLAlchemy (==1.3.18)
Requires-Dist: numpy (==1.19.0)
Provides-Extra: mysql
Requires-Dist: MySQL-python (==1.2.5) ; extra == 'mysql'
Provides-Extra: oracle
Requires-Dist: cx-Oracle (==8.0.0) ; extra == 'oracle'
Provides-Extra: postgres
Requires-Dist: psycopg2-binary (==2.8.5) ; extra == 'postgres'
